{
  "designs": [
    {"file": "01.png", "tags": ["tech", "saas", "dark", "generic"]},
    {"file": "02.png", "tags": ["food", "product", "health", "ecommerce"]},
    {"file": "03.png", "tags": ["tech", "saas", "generic"]},
    {"file": "04.png", "tags": ["finance", "tech", "dark"]},
    {"file": "05.png", "tags": ["finance", "fintech", "dark"]},
    {"file": "06.png", "tags": ["health", "wellness", "product", "nature"]},
    {"file": "07.png", "tags": ["finance", "fintech", "light", "generic"]},
    {"file": "08.png", "tags": ["tech", "saas", "light", "generic"]},
    {"file": "09.png", "tags": ["real_estate", "luxury", "dark"]},
    {"file": "10.png", "tags": ["tech", "saas", "app", "light"]},
    {"file": "11.png", "tags": ["food", "product", "health", "ecommerce"]},
    {"file": "12.png", "tags": ["luxury", "architecture", "outdoor", "fullcover"]},
    {"file": "13.png", "tags": ["luxury", "architecture", "outdoor", "handwerk"]},
    {"file": "14.png", "tags": ["tech", "saas", "dark", "security"]},
    {"file": "15.png", "tags": ["food", "restaurant", "agency", "editorial"]},
    {"file": "16.png", "tags": ["food", "product", "minimal", "light"]},
    {"file": "17.png", "tags": ["tech", "saas", "dark", "generic"]},
    {"file": "18.png", "tags": ["consulting", "finance", "legal", "light"]},
    {"file": "19.png", "tags": ["tech", "saas", "fullcover", "generic"]},
    {"file": "20.png", "tags": ["finance", "tech", "dark", "dashboard"]},
    {"file": "21.png", "tags": ["tech", "saas", "dark", "security"]},
    {"file": "22.png", "tags": ["finance", "fintech", "dark"]}
  ],
  "industry_map": {
    "food":        ["15", "16", "02", "11"],
    "restaurant":  ["15", "16", "02", "11"],
    "cafe":        ["16", "15", "02", "11"],
    "bakery":      ["16", "15", "02", "11"],
    "catering":    ["15", "02", "16", "11"],
    "tech":        ["01", "03", "08", "17", "10", "19"],
    "saas":        ["03", "08", "17", "10", "01", "19"],
    "finance":     ["04", "05", "07", "18", "22", "20"],
    "legal":       ["18", "04", "09", "07"],
    "consulting":  ["18", "04", "08", "07"],
    "real_estate": ["09", "12", "13", "19"],
    "luxury":      ["09", "12", "13", "16"],
    "architecture":["12", "13", "09", "19"],
    "handwerk":    ["13", "12", "19", "09"],
    "health":      ["06", "02", "11", "16"],
    "wellness":    ["06", "11", "16", "02"],
    "medical":     ["06", "08", "16", "07"],
    "dental":      ["08", "06", "07", "16"],
    "beauty":      ["06", "16", "12", "11"],
    "product":     ["02", "11", "06", "16"],
    "generic":     ["03", "08", "19", "07", "16", "12"]
  }
}
